osm4gpd/__init__.py
osm4gpd/__version__.py
osm4gpd/blocks.py
osm4gpd/filter.py
osm4gpd/nodes.py
osm4gpd/parse.py
osm4gpd/proto/__init__.py
osm4gpd/proto/fileformat_pb2.py
osm4gpd/proto/fileformat_pb2.pyi
osm4gpd/proto/osmformat_pb2.py
osm4gpd/proto/osmformat_pb2.pyi
osm4gpd/py.typed
osm4gpd/references.py
osm4gpd/relations.py
osm4gpd/result.py
osm4gpd/tags.py
osm4gpd/unpacked/__init__.py
osm4gpd/unpacked/base.py
osm4gpd/unpacked/nodes.py
osm4gpd/unpacked/relations.py
osm4gpd/unpacked/ways.py
osm4gpd/ways.py
osm4gpd-0.2.0a3.dist-info/LICENSE
osm4gpd-0.2.0a3.dist-info/METADATA
osm4gpd-0.2.0a3.dist-info/WHEEL
osm4gpd-0.2.0a3.dist-info/RECORD
