Metadata-Version: 2.1
Name: osm4gpd
Version: 0.2.0a3
Summary: A parser that loads openstreetmaps native protobuf format into a sparse geopandas dataframe.
License: MIT
Author: Christian
Author-email: christian.knauth@citywalx.net
Requires-Python: >=3.10,<4.0
Classifier: License :: OSI Approved :: MIT License
Classifier: Programming Language :: Python :: 3
Classifier: Programming Language :: Python :: 3.10
Classifier: Programming Language :: Python :: 3.11
Requires-Dist: geopandas (>=0.13.2)
Requires-Dist: numpy (>=1.25.1)
Requires-Dist: pandas (>=2.0.3)
Requires-Dist: protobuf (>=4.23.4)
Requires-Dist: shapely (>=2.0.1)
